connections/__init__.py
constants/__init__.py
constants/constants.py
examples/__init__.py
examples/create_connection.py
examples/execute_query.py
examples/execute_query_async.py
examples/execute_script.py
utilities/__init__.py
utilities/sf_operations.py
snowflake_python_sdk-1.0.0.dist-info/LICENSE
snowflake_python_sdk-1.0.0.dist-info/METADATA
snowflake_python_sdk-1.0.0.dist-info/WHEEL
snowflake_python_sdk-1.0.0.dist-info/top_level.txt
snowflake_python_sdk-1.0.0.dist-info/RECORD
