Metadata-Version: 2.1
Name: snowflake-python-sdk
Version: 1.0.0
Summary: This package has been built to help developers build applications using snowflake quickly
Home-page: https://github.com/Infosys/Snowflake-Python-Development-Framework
Author: Rajib Deb
Author-email: rajib_deb@infosys.com
License: UNKNOWN
Platform: UNKNOWN
Classifier: Programming Language :: Python :: 3
Classifier: License :: OSI Approved :: Apache Software License
Classifier: Operating System :: OS Independent
Requires-Python: >=3.7
Requires-Dist: snowflake-connector-python
Requires-Dist: configparser
